Workbook

Sheet 1.1
A1: Разработка схемы электрической сети
E2: 1.1
A4: данные о нагрузках района
N6: состав | O6: продолж.
A7: № ПС | C7: 220 | D7: кВ | G7: 110 | H7: кВ | K7: 10 | L7: кВ | N7: нагрузки | O7: использов.
A8: на | B8: max | D8: min | F8: max | H8: min | J8: max | L8: min | N8: по кетегории | O8: max
A9: плане | B9: P МВт | C9: tg Ψ | D9: P МВт | E9: tg Ψ | F9: P МВт | G9: tg Ψ | H9: P МВт | I9: tg Ψ | J9: P МВт | K9: tg Ψ | L9: P МВт | M9: tg Ψ | N9: надежности | O9: нагрузки
A10: 1 | F10: 41 | G10: 0.5 | H10: 20 | I10: 0.48 | J10: 24 | K10: 0.5 | L10: 12 | M10: 0.44 | N10: I-III | O10: 4100
A11: 2 | J11: 32 | K11: 0.48 | L11: 12 | M11: 0.44 | N11: I-III | O11: 4000
A12: 3 | J12: 18 | K12: 0.46 | L12: 10 | M12: 0.43 | N12: I-III | O12: 4200
A13: 4 | J13: 10 | K13: 0.47 | L13: 5 | M13: 0.45 | N13: I-III | O13: 4400
A14: 5
A17: 1 Уровни напряжения на шинах ПС А:
K18: в режиме max нагрузок | O18: 1.06 | P18: Uном
K19: в режиме min нагрузок | O19: 1.01 | P19: Uном
A21: 2 Коэффициент реактивной мощности tg(Ψ) на шинах ПС А В режимах :
M22: max нагрузок | O22: 0.3
M23: min нагрузок | O23: 0.45
A25: 3 Коэффициент участия (одновременности) нагрузок района в
A26: максимуме энергосистемы : | N26: Ко= | O26: 1
A27: 4 Величина нагрузки подстанции, предшествующая max нагрузке: | O27: 0.7
A30: 5 Расчетный срок проекта : | N30: Тр= | O30: 5 | P30: лет
A32: 6 Норма дисконта : | N32: Ен= | O32: 12 | P32: %
A34: 7 Цена на электроэнергию : | N34: Цэ= | O34: 1 | P34: руб/кВт час
A36: 8 Условия сооружения и работы сети:
J37: район нагрузок принадлежит ОЭС | O37: Сибири
A39: 9 Климатические районы:
K40: по гололёду | O40: 3
K41: по скростному напору ветра | O41: 3
A51: План распложения источников питания нагрузок района
F54: 2 | I54: 40 км. | K54: 3
I56: 28 км.
G57: 28 км. | K57: 35 км.
F59: 57 км. | H59: 1
I60: 29 км.
C61: ПС А | K61: 4
C63: 110 и 220 кВ.
A67: Анализ исходных данных и выбор вариантов конфигурации сети.
A69: Для проектирования была предложена сеть района нагрузок состоящая из подстанции
A70: энергосистемы – ПС А и четырёх отребительских – ПС 1 , ПС 2 , ПС 3 и ПС 4
A71: Причем потребители на подстанции принадлежат ко всем категориям надежности, что
A72: предусматривает установку на подстанциях двух трансформаторов .
A73: Сеть располагается в зоне Сибири ОЭС и имеет 3-й климатический район по гололеду.
A74: Согласно заданию выбираем два варианта электрических схем сети нагрузок.
H76: Радиальная схема сх 1:
H77: 2 | M77: 3
J82: 1
E84: ПС А | M84: 4
F86: Радиальная схема с кольцевым участком сх 2:
H88: 2 | M88: 3
J93: 1
E95: ПС А | M95: 4
B100: сводная таблица параметров выбранных схем
H102: участки
E103: А - 1 | F103: 1 - 2 | G103: 1 - 3 | H103: 1 - 4 | I103: 2 - 3 | J103: 2 - 4 | K103: 3 - 4
B104: L участков; км | E104: 57 | F104: 28 | G104: 28 | H104: 29 | I104: 40 | K104: 35
B105: тип линии сх1 | E105: 2 | F105: 2 | G105: 2 | H105: 2
B106: тип линии сх2 | E106: 2 | F106: 2 | H106: 1 | I106: 1 | K106: 1

Sheet 1.2
E1: 1.2
A3: Определение приближенного баланса активных и реактивных
A4: мощностей района нагрузок.
B11: Расчет max нагрузок на ПС-1
F13: ='1.1'!F10+'1.1'!J10 -> 65 | G13: МВт
F15: =F13*('1.1'!G10) -> 32.5 | G15: Мвар
F17: =(F13^2+F15^2)^(1/2) -> 72.672209 | G17: МВА
B19: Расчет max нагрузок на ПС-2
F21: ='1.1'!J11 -> 32 | G21: МВт
F23: =F21*'1.1'!K11 -> 15.36 | G23: Мвар
F25: =(F21^2+F23^2)^(1/2) -> 35.495487 | G25: МВА
B27: Расчет max нагрузок на ПС-3
F29: ='1.1'!J12 -> 18 | G29: МВт
F31: =F29*'1.1'!K12 -> 8.28 | G31: Мвар
F33: =(F29^2+F31^2)^(1/2) -> 19.813087 | G33: МВА
B35: Расчет max нагрузок на ПС-4
F37: ='1.1'!J13 -> 10 | G37: МВт
F39: =F37*'1.1'!K13 -> 4.7 | G39: Мвар
F41: =(F37^2+F39^2)^(1/2) -> 11.049434 | G41: МВА
B43: Суммарная max активная мощность сети
F45: ='1.1'!O26*(F13+F21+F29+F37) -> 125 | G45: МВт
B47: Суммарная max реактивная мощность сети
F49: ='1.1'!O26*(F15+F23+F31+F39) -> 60.84 | G49: Мвар
B51: Суммарная max полная мощность сети
F53: ='1.1'!O26*('1.2'!F41+'1.2'!F33+'1.2'!F25+'1.2'!F17) -> 139.03022 | G53: МВА

Sheet 1.3
F1: 1.3
B19: Радиальная схема сх1
E21: =1000/((500/'1.1'!E104)+(2500*'1.1'!E105/'1.2'!F45))^(1/2) -> 143.19077 | F21: кВ | G21: принимаем | I21: =IF(E21>110,220,110) -> 220 | J21: кВ
D22: ='1.1'!E105 -> 2
E25: =1000/((500/'1.1'!F104)+(2500*'1.1'!F105/'1.2'!F21))^(1/2) -> 75.786475 | F25: кВ | G25: принимаем | I25: =IF(E25>110,220,110) -> 110 | J25: кВ
D26: ='1.1'!F105 -> 2
E28: =1000/((500/'1.1'!G104)+(2500*'1.1'!G105/'1.2'!F29))^(1/2) -> 58.159697 | F28: кВ | G28: принимаем | I28: =IF(E28>110,220,110) -> 110 | J28: кВ
D29: ='1.1'!G105 -> 2
E31: =1000/((500/'1.1'!H104)+(2500*'1.1'!H105/'1.2'!F37))^(1/2) -> 43.969687 | F31: кВ | G31: принимаем | I31: =IF(E31>110,220,110) -> 110 | J31: кВ
D32: ='1.1'!H105 -> 2
B35: Радиальная схема с кольцевым участком сх 2:
E37: =1000/((500/'1.1'!E104)+(2500*'1.1'!E106/'1.2'!F45))^(1/2) -> 143.19077 | F37: кВ | G37: принимаем | I37: =IF(E37>110,220,110) -> 220 | J37: кВ
D38: ='1.1'!E106 -> 2
E41: =1000/((500/'1.1'!F104)+(2500*'1.1'!F106/'1.2'!F21))^(1/2) -> 75.786475 | F41: кВ | G41: принимаем | I41: =IF(E41>110,220,110) -> 110 | J41: кВ
D42: ='1.1'!F106 -> 2
E45: =1000/((500/'1.1'!H104)+(2500*'1.1'!H106/'1.2'!F37))^(1/2) -> 61.171362 | F45: кВ | G45: принимаем | I45: =IF(E45>110,220,110) -> 110 | J45: кВ
D46: ='1.1'!H106 -> 1
E51: =1000/((500/'1.1'!I104)+(2500*'1.1'!I106/'1.2'!F29))^(1/2) -> 81.274255 | F51: кВ | G51: принимаем | I51: =IF(E51>110,220,110) -> 110 | J51: кВ
D52: ='1.1'!I106 -> 1
E55: =1000/((500/'1.1'!K104)+(2500*'1.1'!K106/'1.2'!F37))^(1/2) -> 61.512469 | F55: кВ | G55: принимаем | I55: =IF(E55>110,220,110) -> 110 | J55: кВ
D56: ='1.1'!K106 -> 1

Sheet 1.4
F1: 1.4
C14: где - мощность потребителей подстанции.
G16: ='1.2'!F17+'1.2'!F25+'1.2'!F33+'1.2'!F41 -> 139.03022 | H16: МВА
G18: ='1.2'!F25 -> 35.495487 | H18: МВА
G20: ='1.2'!F33 -> 19.813087 | H20: МВА
G22: ='1.2'!F41 -> 11.049434 | H22: МВА
B25: ПС 1
E27: т.е. | G27: =0.7*G16 -> 97.321152 | H27: МВА
A30: По [1] табл. [5.18] выбираем 2 трансформатора АТДЦТН-125000/220/110/0.4
G32: 125 | H32: МВА
G52: =G16/(2*G32) -> 0.55612087
C54: 1
D55: =IF(G52<C54," - условие выполняется"," - УСЛОВИЕ НЕ ВЫПОЛНЯЕТСЯ") -> - условие выполняется
G58: =G16/G32 -> 1.1122417
A66: приинимаем | C66: 1.4
D67: =IF(G58<=C66," - условие выполняется"," - УСЛОВИЕ НЕ ВЫПОЛНЯЕТСЯ") -> - условие выполняется
A72: Так как автотрансформатор не имеет возможности регулирования напряжения со стороны НН,
A73: необходимо выбрать и установить со стороны НН линейный регулировочный трансформатор.
A76: Критерием выбора будет номинальная нагрузка со стороны НН ПС1
B78: =SQRT('1.1'!J10^2+('1.1'!K10*'1.1'!J10)^2) -> 26.832816 | C78: МВА | D78: сответственно выбираем | G78: ЛТДН - 40000/10
B81: ПС 2
E83: т.е. | G83: =0.7*G18 -> 24.846841 | H83: МВА
A86: По [1] табл. [5.13] выбираем 2 трансформатора ТРДН-25000/110/6,3
G88: 25 | H88: МВА
G93: =G18/(2*G88) -> 0.70990974
C95: 1
D96: =IF(G93<C95," - условие выполняется"," - УСЛОВИЕ НЕ ВЫПОЛНЯЕТСЯ") -> - условие выполняется
G102: =G18/G88 -> 1.4198195
A104: приинимаем | C104: 1.5
D105: =IF(G102<=C104," - условие выполняется"," - УСЛОВИЕ НЕ ВЫПОЛНЯЕТСЯ") -> - условие выполняется
B113: ПС 3
E115: т.е. | G115: =0.7*G20 -> 13.869161 | H115: МВА
A118: По [1] табл. [5.13] выбираем 2 трансформатора ТДН-16000/110/6,6
G120: 16 | H120: МВА
G125: =G20/(2*G120) -> 0.61915896
C127: 1
D128: =IF(G125<C127," - условие выполняется"," - УСЛОВИЕ НЕ ВЫПОЛНЯЕТСЯ") -> - условие выполняется
G131: =G20/G120 -> 1.2383179
A133: приинимаем | C133: 1.3
D134: =IF(G131<=C133," - условие выполняется"," - УСЛОВИЕ НЕ ВЫПОЛНЯЕТСЯ") -> - условие выполняется
B138: ПС 4
E140: т.е. | G140: =0.7*G22 -> 7.7346041 | H140: МВА
A143: По [1] табл. [5.13] выбираем 2 трансформатора ТДН-10000/110/6,6
G145: 10 | H145: МВА
G153: =G22/(2*G145) -> 0.55247172
C155: 1
D156: =IF(G153<C155," - условие выполняется"," - УСЛОВИЕ НЕ ВЫПОЛНЯЕТСЯ") -> - условие выполняется
G159: =G22/G145 -> 1.1049434
A161: приинимаем | C161: 1.3
D162: =IF(G159<=C161," - условие выполняется"," - УСЛОВИЕ НЕ ВЫПОЛНЯЕТСЯ") -> - условие выполняется

Sheet параметры тр-ров
B6: число | D6: мощн.
A7: № ПС | B7: тр-ров | D7: тр-ра
B8: на ПС | D8: МВА | E8: ВН | F8: СН | G8: НН | H8: кВт | I8: кВар | J8: ВН | K8: СН | L8: НН | M8: ВН | N8: СН | O8: НН
A9: 1 | B9: 2 | C9: АТДЦТН-125000/220/110 | D9: 125 | E9: 230 | F9: 121 | G9: 10.5 | H9: 65 | I9: 625 | J9: 0.52 | K9: 0.52 | L9: 3.2 | M9: 49 | N9: 0 | O9: 131
A10: 1 | B10: 2 | C10: ЛТДН - 40000/10 | D10: 40 | E10: =G9 -> 10.5 | G10: 11 | H10: 18.5 | O10: 0.03
A11: 2 | B11: 2 | C11: ТРДН-25000/110/10,5 | D11: 25 | E11: 115 | G11: 10.5 | H11: 27 | I11: 175 | J11: 2.54 | M11: 55.9
A12: 3 | B12: 2 | C12: ТДН-16000/110/11 | D12: 16 | E12: 115 | G12: 11 | H12: 19 | I12: 112 | J12: 4.38 | M12: 86.7
A13: 4 | B13: 2 | C13: ТДН-10000/110/11 | D13: 10 | E13: 115 | G13: 11 | H13: 14 | I13: 70 | J13: 7.95 | M13: 139

Sheet 1.5
E1: 1.5
E7: участок 1-2
B18: = | C18: =COMPLEX('1.2'!F21,'1.2'!F23,"j") -> 32+15,36j | D18: = | E18: =IMABS(C18) -> 35.495487 | G18: МВА
C20: = | D20: =IMSUM(C18,IMPRODUCT(E24,10^-6)) -> 32,0000001322405+15,3600029103332j | F20: МВА
C22: = | D22: =IMDIV(COMPLEX(PRODUCT('параметры тр-ров'!J11,10^-6),PRODUCT('параметры тр-ров'!M11,10^-6),"j"),2) -> 0,00000127+0,00002795j | F22: МВА
D24: = | E24: =IMPRODUCT(IMDIV(IMPOWER(E18,2),IMPOWER('1.1'!G7,2)),IMPRODUCT(D22,10^3),10^3) -> 0,132240544793388+2,91033324958676j | H24: =IMABS(E24) -> 2.9133361 | I24: ВА
E25: =IMREAL(E24) -> 0.13224054
C28: = | D28: =IMSUM(D20,IMPRODUCT(2,COMPLEX(IMPRODUCT('параметры тр-ров'!H11,POWER(10,-3)),(IMPRODUCT('параметры тр-ров'!I11,POWER(10,-3))),"j"))) -> 32,0540001322405+15,7100029103332j | G28: = | H28: =IMABS(D28) -> 35.696822 | I28: МВА
E31: Выбор проводов
C34: = | D34: =(PRODUCT(H28,POWER(10,3)))/(PRODUCT(SQRT(3),'1.1'!G7,2)) -> 93.679863 | E34: А
B36: 1.1 | C36: - для алюминиевых неизолированных проводов
C38: =D34/B36 -> 85.163512 | D38: =IF(C38>=F40," - условие короны выполняется"," - УСЛОВИЕ КОРОНЫ НЕ ВЫПОЛНЯЕТСЯ") -> - условие короны выполняется
B40: По условию короны для Uном= 110 кВ F ≥ | F40: 70
B42: По [2] таблица [П2.5] выбран провод марки АС-95/16
B44: По [2] таблица [П2.8] Iдоп= | E44: 330 | F44: А
D46: =PRODUCT(H28,POWER(10,3))/PRODUCT(SQRT(3),'1.3'!I25) -> 187.35973 | E46: А
B48: Условие по нагреву: Iп/а ≤ lдоп | E48: =IF(D46<=E44," - выполняется","- НЕ ВЫПОЛНЯЕТСЯ") -> - выполняется
B52: Окончательно выбран провод марки АС - 95/16 со следующими параметрами:
E54: 0.301 | F54: Ом/км
E55: 0.434 | F55: Ом/км
E56: 2.611 | F56: См/км
E58: =(PRODUCT(E54,'1.1'!F104)/2) -> 4.214 | F58: Ом
E60: =(PRODUCT(E55,30.3)/2) -> 6.5751 | F60: Ом
E62: =('1.3'!I25^2)*(E56*10^-6)*'1.1'!F104 -> 0.8846068 | F62: Мвар
B65: Мощность в конце линии с учетом зарядной мощности в конце линии
D67: =IMSUM(D28,COMPLEX(0,-E62,"j")) -> 32,0540001322405+14,8253961103332j | G67: = | H67: =IMABS(D67) -> 35.316445 | I67: МВА
B69: Мощность в начале линии
D71: =IMSUM(D73,COMPLEX(0,-E62,"j")) -> 32,0540003494272+13,9407896492093j
D73: =IMSUM(D67,IMPRODUCT(E75,10^-6)) -> 32,0540003494272+14,8253964492093j | I73: МВА
E75: =IMPRODUCT(IMDIV(IMPOWER(H67,2),IMPOWER('1.1'!G7,2)),IMDIV(COMPLEX(PRODUCT(E58,10^-3),PRODUCT(E60,10^-3),"j"),2),10^3) -> 0,21718665100022+0,338876115090542j | H75: =IMABS(E75) -> 0.40250101 | I75: ВА
E76: =IMREAL(E75) -> 0.21718665
E78: участок 1-3
B89: = | C89: =COMPLEX('1.2'!F29,'1.2'!F31,"j") -> 18+8,28j | D89: = | E89: =IMABS(C89) -> 19.813087 | F89: МВА
C91: = | D91: =IMSUM(C89,IMPRODUCT(E95,10^-6)) -> 18,0000000710498+8,28000140639724j | I91: МВА
C93: = | D93: =IMDIV(COMPLEX(PRODUCT('параметры тр-ров'!J12,10^-6),PRODUCT('параметры тр-ров'!M12,10^-6),"j"),2) -> 0,00000219+0,00004335j | F93: МВА
D95: = | E95: =IMPRODUCT(IMDIV(IMPOWER(E89,2),IMPOWER('1.1'!G7,2)),IMPRODUCT(D93,10^3),10^3) -> 0,0710498261157025+1,40639724297521j | H95: =IMABS(E95) -> 1.4081908 | I95: ВА
E96: =IMREAL(E95) -> 0.071049826
C99: = | D99: =IMSUM(D91,IMPRODUCT(2,COMPLEX(IMPRODUCT('параметры тр-ров'!H12,10^-3),(IMPRODUCT('параметры тр-ров'!I12,10^-3)),"j"))) -> 18,0380000710498+8,50400140639724j | H99: =IMABS(D99) -> 19.942103 | I99: МВА
E102: Выбор проводов
C105: = | D105: =(PRODUCT(H99,POWER(10,3)))/(PRODUCT(SQRT(3),'1.1'!G7,2)) -> 52.334449 | E105: А
B107: 1.1 | C107: - для алюминиевых неизолированных проводов
C109: =D105/B107 -> 47.576772 | D109: =IF(C109>=F111," - условие короны выполняется"," - УСЛОВИЕ КОРОНЫ НЕ ВЫПОЛНЯЕТСЯ") -> - УСЛОВИЕ КОРОНЫ НЕ ВЫПОЛНЯЕТСЯ
B111: По условию короны для Uном= 110 кВ F ≥ | F111: 70
B113: По [2] таблица [П2.5] выбран провод марки АС-70/11
B115: По [2] таблица [П2.8] Iдоп= | E115: 265 | F115: А
D117: =PRODUCT(H99,POWER(10,3)/PRODUCT(SQRT(3),'1.3'!I28)) -> 104.6689 | E117: А
B119: Условие по нагреву: Iп/а ≤ lдоп | E119: =IF(D117<=E115," - выполняется","- НЕ ВЫПОЛНЯЕТСЯ") -> - выполняется
B123: Окончательно выбран провод марки АС - 70/11 со следующими параметрами:
E125: 0.422 | F125: Ом/км
E126: 0.444 | F126: Ом/км
E127: 2.547 | F127: См/км
E129: =(PRODUCT(E125,'1.1'!G104)/2) -> 5.908 | F129: Ом
E131: =PRODUCT(E126,'1.1'!G104)/2 -> 6.216 | F131: Ом
E133: =('1.3'!I28^2)*(E127*10^-6)*'1.1'!G104 -> 0.8629236 | F133: Мвар
B136: Мощность в конце линии с учетом зарядной мощности в конце линии
D138: =IMSUM(D99,COMPLEX(0,-E133,"j")) -> 18,0380000710498+7,64107780639724j | H138: = | I138: =IMABS(D138) -> 19.589679 | J138: МВА
B140: Мощность в начале линии
D142: =IMSUM(D144,COMPLEX(0,-E133,"j")) -> 18,0380001647369+6,77815430496849j
D144: =IMSUM(D138,IMPRODUCT(E146,10^-6)) -> 18,0380001647369+7,64107790496849j | J144: МВА
E146: =IMPRODUCT(IMDIV(IMPOWER(I138,2),IMPOWER('1.3'!I28,2)),IMDIV(COMPLEX(PRODUCT(E129,10^-3),PRODUCT(E131,10^-3),"j"),2),10^3) -> 0,0936870905831341+0,0985712517035818j | I146: =IMABS(E146) -> 0.13599104 | J146: ВА
E147: =IMREAL(E146) -> 0.093687091
E151: участок 1-4
B162: = | C162: =COMPLEX('1.2'!F37,'1.2'!F39,"j") -> 10+4,7j | D162: = | E162: =IMABS(C162) -> 11.049434 | F162: МВА
C164: = | D164: =IMSUM(C162,IMPRODUCT(E168,10^-6)) -> 10,0000000401081+4,70000070126074j | H164: = | I164: =IMABS(D164) -> 11.049435 | J164: МВА
C166: = | D166: =IMDIV(COMPLEX(PRODUCT('параметры тр-ров'!J13,10^-6),PRODUCT('параметры тр-ров'!M13,10^-6),"j"),2) -> 0,000003975+0,0000695j | F166: МВА
D168: = | E168: =IMPRODUCT(IMDIV(IMPOWER(E162,2),IMPOWER('1.3'!I31,2)),IMPRODUCT(D166,10^3),10^3) -> 0,0401080785123967+0,701260743801653j | I168: =IMABS(E168) -> 0.70240678 | J168: ВА
E169: =IMREAL(E168) -> 0.040108079
C172: = | D172: =IMSUM(D164,IMPRODUCT(2,COMPLEX(IMPRODUCT('параметры тр-ров'!H13,10^-3),(IMPRODUCT('параметры тр-ров'!I13,10^-3)),"j"))) -> 10,0280000401081+4,84000070126074j | H172: =IMABS(D172) -> 11.134918 | I172: МВА
E175: Выбор проводов
C178: = | D178: =(PRODUCT(H172,POWER(10,3)))/(PRODUCT(SQRT(3),'1.3'!I31,2)) -> 29.221581 | E178: А
B180: 1.1 | C180: - для алюминиевых неизолированных проводов
C182: =D178/B180 -> 26.565073 | D182: =IF(C182>=F184," - условие короны выполняется"," - УСЛОВИЕ КОРОНЫ НЕ ВЫПОЛНЯЕТСЯ") -> - УСЛОВИЕ КОРОНЫ НЕ ВЫПОЛНЯЕТСЯ
B184: По условию короны для Uном= 110 кВ F ≥ | F184: 70
B186: По [2] таблица [П2.5] выбран провод марки АС-70/11
B188: По [2] таблица [П2.8] Iдоп= | E188: 265 | F188: А
D190: =PRODUCT(H172,POWER(10,3)/PRODUCT(SQRT(3),'1.3'!I31)) -> 58.443161 | E190: А
B192: Условие по нагреву: Iп/а ≤ lдоп | E192: =IF(D190<=E188," - выполняется","- НЕ ВЫПОЛНЯЕТСЯ") -> - выполняется
B196: Окончательно выбран провод марки АС - 70/11 со следующими параметрами:
E198: 0.422 | F198: Ом/км
E199: 0.444 | F199: Ом/км
E200: 2.547 | F200: См/км
E202: =(PRODUCT(E198,'1.1'!H104)/2) -> 6.119 | F202: Ом
E204: =PRODUCT(E199,'1.1'!H104)/2 -> 6.438 | F204: Ом
E206: =('1.3'!I31^2)*(E200*10^-6)*'1.1'!H104 -> 0.8937423 | F206: Мвар
B209: Мощность в конце линии с учетом зарядной мощности в конце линии
D211: =IMSUM(D172,COMPLEX(0,-E206,"j")) -> 10,0280000401081+3,94625840126074j | H211: = | I211: =IMABS(D211) -> 10.776537 | J211: МВА
B213: Мощность в начале линии
D215: =IMSUM(D217,COMPLEX(0,-E206,"j")) -> 11,0279968847746+3,05251691205504j
D217: =IMSUM(D211,IMPOWER(E219,10^-6)) -> 11,0279968847746+3,94625921205504j | J217: МВА
E219: =IMPRODUCT(IMDIV(IMPOWER(I211,2),IMPOWER('1.3'!I31,2)),IMDIV(COMPLEX(PRODUCT(E202,10^-3),PRODUCT(E204,10^-3),"j"),2),10^3) -> 0,0293645601704244+0,0308954140181717j | I219: =IMABS(E219) -> 0.042623984 | J219: ВА
E220: =IMREAL(E219) -> 0.02936456
E222: участок А-1
B236: Мощность в начале звена обмотки СН трансформатора подстанции 1.
B239: =
C241: =IMSUM(D217,D144,D73) -> 61,1199973989387+26,4127335662328j | G241: = | H241: =IMABS(C241) -> 66.58293 | J241: МВА
E243: =IMSUM(C241,IMPRODUCT(E247,10^-6),COMPLEX('1.1'!F10,'1.1'!F10*'1.1'!G10,"j")) -> 102,119997422754+46,9127335662328j | J243: МВА
C245: = | D245: =IMDIV(COMPLEX(PRODUCT('параметры тр-ров'!K9,10^-6),PRODUCT('параметры тр-ров'!N9,10^-6),"j"),2) -> 0,00000026 | F245: МВА
D247: = | E247: =IMPRODUCT(IMDIV(IMPOWER(H241,2),IMPOWER('1.3'!I21,2)),IMPRODUCT(D245,10^3),10^3) -> 0,0238151758241041 | I247: =IMABS(E247) -> 0.023815176 | J247: ВА
E248: =IMREAL(E247) -> 0.023815176
C251: = | D251: =IMSUM(E243,IMPRODUCT(2,COMPLEX(IMPRODUCT('параметры тр-ров'!H9,POWER(10,-3)),(IMPRODUCT('параметры тр-ров'!I9,POWER(10,-3))),"j"))) -> 102,249997422754+48,1627335662328j | H251: =IMABS(D251) -> 113.02527 | I251: МВА
...

Sheet 1.6
F1: 1.6
E15: участок 3-1
D18: ='1.5'!D99 -> 18,0380000710498+8,50400140639724j | H18: =IMABS(D18) -> 19.942103 | I18: МВА
E21: Выбор проводов
D24: =(PRODUCT(H18,POWER(10,3)))/(PRODUCT(SQRT(3),'1.3'!I41)) -> 104.6689 | E24: А
B26: 1.1 | C26: - для алюминиевых неизолированных проводов
C28: =D24/B26 -> 95.153543 | D28: =IF(C28>=F30," - условие короны выполняется"," - УСЛОВИЕ КОРОНЫ НЕ ВЫПОЛНЯЕТСЯ") -> - условие короны выполняется
B30: По условию короны для Uном= 110 кВ F ≥ | F30: 70
B32: По [2] таблица [П2.5] выбран провод марки АС-70/11
B34: По [2] таблица [П2.8] Iдоп= | E34: 265 | F34: А
D36: =(PRODUCT(H18,POWER(10,3))+PRODUCT(H67,POWER(10,3)))/PRODUCT(SQRT(3),'1.3'!I45) -> 163.11206 | E36: А
B38: Условие по нагреву: Iп/а ≤ lдоп | E38: - выполняется
B40: Окончательно выбран провод марки АС - 70/11 со следующими параметрами:
E42: 0.422 | F42: Ом/км
E43: 0.444 | F43: Ом/км
E44: 2.547 | F44: См/км
E46: =PRODUCT(E42,'1.1'!G104) -> 11.816 | F46: Ом
E48: =PRODUCT(E43,'1.1'!G104) -> 12.432 | F48: Ом
E50: =('1.3'!I45^2)*(E44*10^-6)*'1.1'!G104 -> 0.8629236 | F50: Мвар
B51: Мощность в конце линии с учетом зарядной мощности в конце линии
D53: =IMSUM(D18,COMPLEX(0,-E50/2,"j")) -> 18,0380000710498+8,07253960639724j | H53: = | I53: =IMABS(D53) -> 19.761967 | J53: МВА
B55: Мощность в начале линии
D57: =IMSUM(D59,COMPLEX(0,-E50,"j")) -> 18,0380004524189+7,2096164076481j | J57: МВА
D59: =IMSUM(D53,IMPRODUCT(E61,10^-6)) -> 18,0380004524189+8,0725400076481j | J59: МВА
E61: =IMPRODUCT(IMDIV(IMPOWER(I53,2),IMPOWER('1.3'!I41,2)),(COMPLEX(PRODUCT(E46,10^-3),PRODUCT(E48,10^-3),"j")),10^3) -> 0,381369058193776+0,401250857436106j | I61: =IMABS(E61) -> 0.55357439 | J61: ВА
E62: =IMREAL(E61) -> 0.38136906
E64: участок 4-1'
D67: ='1.5'!D172 -> 10,0280000401081+4,84000070126074j | H67: =IMABS(D67) -> 11.134918 | I67: МВА
E70: Выбор проводов
D73: =(PRODUCT(H67,POWER(10,3)))/(PRODUCT(SQRT(3),'1.3'!I45)) -> 58.443161 | E73: А
B75: 1.1 | C75: - для алюминиевых неизолированных проводов
C77: =D73/B75 -> 53.130146 | D77: =IF(C77>=F79," - условие короны выполняется"," - УСЛОВИЕ КОРОНЫ НЕ ВЫПОЛНЯЕТСЯ") -> - УСЛОВИЕ КОРОНЫ НЕ ВЫПОЛНЯЕТСЯ
B79: По условию короны для Uном= 110 кВ F ≥ | F79: 70
B81: По [2] таблица [П2.5] выбран провод марки АС-70/11
B83: По [2] таблица [П2.8] Iдоп= | E83: 265 | F83: А
D86: =(PRODUCT(H18,POWER(10,3))+PRODUCT(H67,POWER(10,3)))/PRODUCT(SQRT(3),'1.3'!I45) -> 163.11206 | E86: А
B89: Окончательно выбран провод марки АС - 70/11 со следующими параметрами:
E91: 0.422 | F91: Ом/км
E92: 0.444 | F92: Ом/км
E93: 2.547 | F93: См/км
E95: =PRODUCT(E91,'1.1'!H104) -> 12.238 | F95: Ом
E97: =PRODUCT(E92,'1.1'!H104) -> 12.876 | F97: Ом
E99: =('1.3'!I45^2)*(E93*10^-6)*'1.1'!H104 -> 0.8937423 | F99: Мвар
B103: Мощность в конце линии с учетом зарядной мощности в конце линии
D105: =IMSUM(D67,COMPLEX(0,-E143/2,"j")) -> 10,0280000401081+4,30067345126074j | H105: = | I105: =IMABS(D105) -> 10.911305 | J105: МВА
B107: Мощность в начале линии
D109: =IMSUM(D111,COMPLEX(0,-E143,"j")) -> 10,0280001605225+3,22201907795268j | J109: МВА
D111: =IMSUM(D105,IMPRODUCT(E113,10^-6)) -> 10,0280001605225+4,30067357795268j | J111: МВА
E113: =IMPRODUCT(IMDIV(IMPOWER(I105,2),IMPOWER('1.3'!I45,2)),(COMPLEX(PRODUCT(E95,POWER(10,-3)),PRODUCT(E97,POWER(10,-3)),"j")),10^3) -> 0,120414412279081+0,126691940881308j | I113: =IMABS(E113) -> 0.17478695 | J113: Ом
E114: =IMREAL(E113) -> 0.12041441
E116: участок 3-4
B118: Выбор проводов производим по наиболие тяжелому послеаварийному режиму
B120: при обрыве участка 1-3
D122: =(PRODUCT(H18,10^3))/PRODUCT(SQRT(3),'1.3'!I55) -> 104.6689 | E122: А
B124: при обрыве участка 1-4
D126: =(PRODUCT(H67,10^3))/PRODUCT(SQRT(3),'1.3'!I55) -> 58.443161 | E126: А
B129: I max п/а= | C129: =IF(D122>D126,D122,D126) -> 104.6689 | D129: А
B131: По [2] таблица [П2.8] Iдоп= | E131: 265 | F131: А
B133: Выбираем провод марки АС - 70/11 с параметрами:
E135: 0.422 | F135: Ом/км
E136: 0.444 | F136: Ом/км
E137: 2.547 | F137: См/км
E139: =PRODUCT(E135,'1.1'!K104) -> 14.77 | F139: Ом
E141: =PRODUCT(E136,'1.1'!K104) -> 15.54 | F141: Ом
E143: =('1.3'!I45^2)*(E137*10^-6)*'1.1'!K104 -> 1.0786545 | F143: Мвар

Sheet потокораздел
B21: Сопряженные комплексы сопротивлений участков
F23: =COMPLEX('1.6'!E46,-'1.6'!E48,"j") -> 11,816-12,432j | H23: Ом
F24: =COMPLEX('1.6'!E95,-'1.6'!E97,"j") -> 12,238-12,876j | H24: Ом
F25: =COMPLEX('1.6'!E139,-'1.6'!E141,"j") -> 14,77-15,54j | H25: Ом
F26: =IMSUM(F23,F24,F25) -> 38,824-40,848j | H26: Ом
F29: =IMDIV(IMSUM(IMPRODUCT('1.6'!D18,IMSUM(F25,F24)),IMPRODUCT('1.6'!D67,F24)),F26) -> 15,7091739751122+7,44147946028243j | J29: МВА
F32: =IMDIV(IMSUM(IMPRODUCT('1.6'!D67,IMSUM(F25,F23)),IMPRODUCT('1.6'!D18,F23)),F26) -> 12,3568261360457+5,90252264737553j | J32: МВА
F35: =IMSUB(F32,'1.6'!D67) -> 2,3288260959376+1,06252194611479j | J35: МВА
B38: Разрываем схему на два радиальных участка
E51: участок 3-1
B53: Мощность в конце линии с учетом зарядной мощности в конце линии
D55: =IMSUM(F29,COMPLEX(0,'1.6'!E50/2,"j")) -> 15,7091739751122+7,87294126028243j | J55: МВА
B57: Мощность в начале линии
D59: =IMSUM(D61,COMPLEX(0,-'1.5'!E133,"j")) -> 15,7091739014281+7,01001809169691j
D61: =IMSUM(D55,IMPRODUCT(E63,10^-6)) -> 15,7091739014281+7,87294169169691j | J61: МВА
E63: =IMPRODUCT(IMDIV(IMPOWER(D55,2),IMPOWER('1.3'!I41,2)),(COMPLEX(PRODUCT('1.6'!E46,10^-3),PRODUCT('1.6'!E48,10^-3),"j")),10^3) -> -0,0736841261723232+0,43141447440258j | J63: ВА
E66: участок 4-1'
B68: Мощность в конце линии с учетом зарядной мощности в конце линии
D70: =IMSUM(F32,COMPLEX(0,'1.6'!E99/2,"j")) -> 12,3568261360457+6,34939379737553j | H70: = | I70: =IMABS(D70) -> 13.892658 | J70: МВА
B72: Мощность в начале линии
D74: =IMSUM(D76,COMPLEX(0,-'1.5'!E206,"j")) -> 12,3568263312529+5,45565170275939j
D76: =IMSUM(D70,IMPRODUCT(E78,10^-6)) -> 12,3568263312529+6,34939400275939j | J76: МВА
E78: =IMPRODUCT(IMDIV(IMPOWER(I70,2),IMPOWER('1.3'!I31,2)),(COMPLEX(PRODUCT('1.6'!E95,10^-3),PRODUCT('1.6'!E97,10^-3),"j")),10^3) -> 0,195207178677686+0,205383856239082j | J78: Ом
B81: Мощность поступающая в кольцо
D83: =IMSUM(D55,D70) -> 28,0660001111579+14,222335057658j | J83: МВА
E87: участок 1-2
B91: Аналогичен расчету в радиальной схеме
E101: участок А-1
B115: Мощность в начале звена обмотки СН трансформатора подстанции 1.
B118: =
C120: =D83 -> 28,0660001111579+14,222335057658j | G120: = | H120: =IMABS(C120) -> 31.463871 | I120: МВА
E122: =IMSUM(C120,IMPRODUCT(E126,10^-6),COMPLEX('1.1'!F10,'1.1'!F10*'1.1'!G10,"j")) -> 69,0659997101904+34,722335358288j | I122: МВА
C124: = | D124: =IMDIV(COMPLEX(PRODUCT('параметры тр-ров'!J9,10^-6),PRODUCT('параметры тр-ров'!M9,10^-6),"j"),2) -> 0,00000026+0,0000245j | G124: МВА = | H124: =IMPRODUCT(D124,POWER(10,6)) -> 0,26+24,5j | I124: ВА
D126: = | E126: =IMPRODUCT(IMDIV(IMPOWER(C120,2),IMPOWER('1.3'!I21,2)),IMPRODUCT(D124,10^3),10^3) -> -0,400967524085418+0,300629984082808j | I126: ВА
C130: = | D130: =IMSUM(E122,IMPRODUCT(2,COMPLEX(IMPRODUCT('параметры тр-ров'!J9,POWER(10,-3)),(IMPRODUCT('параметры тр-ров'!M9,POWER(10,-3))),"j"))) -> 69,0670397101904+34,820335358288j | G130: = | H130: =IMABS(D130) -> 77.347991 | I130: МВА
B133: Мощность в начале звена обмотки НН трансформатора подстанции 1.
B136: = | C136: =COMPLEX('1.1'!J10,'1.1'!J10*'1.1'!K10,"j") -> 24+12j | D136: = | E136: =IMABS(C136) -> 26.832816 | G136: МВА
C138: = | D138: =IMSUM(C136,IMPOWER(E142,10^-6)) -> 25,0000061564472+12,0000015463832j | H138: = | I138: =IMABS(D138) -> 27.730855 | J138: МВА
C140: = | D140: =IMDIV(COMPLEX(PRODUCT('параметры тр-ров'!L9,POWER(10,-6)),PRODUCT('параметры тр-ров'!O9,POWER(10,-6)),"j"),2) -> 0,0000016+0,0000655j | F140: МВА = | G140: =IMPRODUCT(D140,POWER(10,6)) -> 1,6+65,5j | J140: ВА
D142: = | E142: =IMPRODUCT(IMDIV(IMPOWER(E136,2),IMPOWER('1.1'!K7,2)),IMPRODUCT(D140,10^3),10^3) -> 11,52+471,6j | J142: ВА
C146: = | D146: =IMSUM(D138,IMPRODUCT(2,COMPLEX(IMPRODUCT('параметры тр-ров'!H9,POWER(10,-3)),(IMPRODUCT('параметры тр-ров'!I9,POWER(10,-3))),"j"))) -> 25,1300061564472+13,2500015463832j | H146: = | I146: =IMABS(D146) -> 28.409149 | J146: МВА
B149: Мощность в начале звена обмотки ВН трансформатора подстанции 1.
D152: =IMSUM(C120,C136) -> 52,0660001111579+26,222335057658j | H152: = | I152: =IMABS(D152) -> 58.296477 | J152: МВА
D154: =IMSUM(D152,IMPOWER(E158,10^-6),"j") -> 53,0660006537145+27,2223366178433j | J154: МВА
C156: = | D156: =IMDIV(COMPLEX(PRODUCT('параметры тр-ров'!J9,POWER(10,-6)),PRODUCT('параметры тр-ров'!M9,POWER(10,-6)),"j"),2) -> 0,00000026+0,0000245j | F156: МВА = | G156: =IMPRODUCT(D156,POWER(10,6)) -> 0,26+24,5j | J156: ВА
D158: = | E158: =IMPRODUCT(IMDIV(IMPOWER(I152,2),IMPOWER('1.3'!I37,2)),IMPRODUCT(D156,10^3),10^3) -> 0,0182562933491179+1,72030456558996j | J158: ВА
C162: = | D162: =IMSUM(D154,IMPRODUCT(2,COMPLEX(IMPRODUCT('параметры тр-ров'!H9,POWER(10,-3)),(IMPRODUCT('параметры тр-ров'!I9,POWER(10,-3))),"j"))) -> 53,1960006537145+28,4723366178433j | H162: = | I162: =IMABS(D162) -> 60.33646 | J162: МВА
E165: Выбор проводов
C168: = | D168: =(PRODUCT(I162,POWER(10,3)))/(PRODUCT(SQRT(3),'1.3'!I37,2)) -> 79.171072 | E168: А
B170: 1.1 | C170: - для алюминиевых неизолированных проводов
C172: =D168/B170 -> 71.973702 | D172: =IF(C172>=F174," - условие короны выполняется"," - УСЛОВИЕ КОРОНЫ НЕ ВЫПОЛНЯЕТСЯ") -> - УСЛОВИЕ КОРОНЫ НЕ ВЫПОЛНЯЕТСЯ
B174: По условию короны для Uном= 220 кВ F ≥ | F174: 240
B176: По [2] таблица [П2.4] выбран провод марки АС-240/32
B178: По [2] таблица [П2.8] Iдоп= | E178: 610 | F178: А
D181: =PRODUCT(I162,POWER(10,3)/PRODUCT(SQRT(3),'1.3'!I37)) -> 158.34214 | E181: А
B183: Условие по нагреву: Iп/а ≤ lдоп | E183: =IF(D181<=E178," - выполняется","- НЕ ВЫПОЛНЯЕТСЯ") -> - выполняется
B187: Окончательно выбран провод марки АС-240/32 со следующими параметрами:
E189: 0.118 | F189: Ом/км
E190: 0.435 | F190: Ом/км
E191: 2.604 | F191: См/км
E193: =(PRODUCT(E189,'1.1'!E104)/2) -> 3.363 | F193: Ом
E195: =PRODUCT(E190,'1.1'!E104)/2 -> 12.3975 | F195: Ом
E197: =('1.3'!I37^2)*(E191*10^-6)*'1.1'!E104 -> 7.1839152 | F197: Мвар
B201: Мощность в конце линии с учетом зарядной мощности в конце линии
D203: =IMSUM(I162,COMPLEX(0,-E197,"j")) -> 60,3364602709653-7,1839152j | G203: = | H203: =IMABS(D203) -> 60.762629 | I203: МВА
B205: Мощность в начале линии
D207: =IMSUM(D209,COMPLEX(0,-E197,"j")) -> 61,3364595575086-14,3678290940945j | I207: МВА
D209: =IMSUM(D203,IMPOWER(E211,10^-6)) -> 61,3364595575086-7,18391389409452j | I209: МВА
E211: =IMPRODUCT(IMDIV(IMPOWER(H203,2),IMPOWER('1.3'!I37,2)),IMDIV(COMPLEX(PRODUCT(E193,POWER(10,-3)),PRODUCT(E195,POWER(10,-3)),"j"),2),10^3) -> 0,12826986017919+0,47285923032159j | I211: ВА

Sheet РУ ПС
E19: Данные по схемам РУ ПС в соответствиии с [5]

Sheet ТЭС
B14: Радиальная сеть
B16: Кап вложения в ЛЭП
B18: участок | C18: Uном кВ | D18: Район | E18: марка | F18: число | G18: тип | H18: длина | I18: стоимость тыс. руб.
D19: ОЭС | E19: провода | F19: цепей | G19: опор | H19: линии км | I19: 1 км | J19: сумма
B20: ='1.1'!G103 -> 1 - 3 | C20: 110 | D20: сибирь | E20: АС - 70/11 | F20: 2 | G20: ж/б | H20: ='1.1'!G104 -> 28 | I20: 57 | J20: =I20*H24*H20*H25*F20 -> 153216
B21: ='1.1'!H103 -> 1 - 4 | C21: 110 | D21: сибирь | E21: АС - 70/11 | F21: 2 | G21: ж/б | H21: ='1.1'!H104 -> 29 | I21: 57 | J21: =I21*H24*H21*H25*F21 -> 158688
I22: Итого | J22: =SUM(J20:J21) -> 311904
B24: Коэффициент удорожания Кдэф (дефирования) принимаем = | H24: 40
B25: Зональный повышающий коэффициент на стоимость = | H25: 1.2
B29: Капитальные вложения в ПС
E31: =I42+C35*C33*H24 -> 136928 | F31: тыс.руб.
C33: 430 | D33: тыс.руб.
C35: 2 | D35: - число подстанций
C36: 2 | D36: - число выключателей на ПС
C37: 2 | D37: - разница колличества выключателей РУСН ПС 1, для радиальной и
D38: кольцевой схемы
C39: принимаем во внимание то, что при стоительстве РУСН ПС1 радиальной схемы, по сравнению
C40: с кольцевой схемой, РУСН ПС1 радиальной схемы имеет на ∆n выключателей больше.
I42: =(C35*C46+C35*C36*C44+C37*C44)*H24*H25 -> 102528 | J42: тыс.руб.
C44: 290 | D44: тыс.руб.
C46: 198 | D46: тыс.руб. | E46: по[2 П2.10]
B48: Сумарные вложения
D50: =J22+E31 -> 448832 | E50: тыс.руб.
B51: Ежегодные издержки на амортизацию и обслуживание ПС
D53: =I57*I42*I56/100/100 -> 3206.0506 | E53: тыс.руб.
B56: составляющая стоимости оборудования по ПС | I56: 53 | J56: %
B57: α - нормы отчислений на ремонты и обслуживание для ПС | I57: 5.9 | J57: %
B59: Ежегодные издержки на амортизацию и обслуживание ЛЭП
D61: =I65*I64*J22/100/100 -> 174.66624 | E61: тыс.руб.
B64: составляющая стоимости оборудования по ВЛ | I64: 7 | J64: %
B65: α - нормы отчислений на ремонты и обслуживание для ВЛ | I65: 0.8 | J65: %
B68: определим средневзвешенное время максимальных потерь τ
E71: =(0.124+(F75/10000))^2*8760 -> 2786.4872 | F71: ч.
F75: =(SQRT((('1.2'!F29+'1.2'!F37)*'1.1'!O13)^2+(('1.2'!F39+'1.2'!F31)*'1.1'!O13)^2)/('1.2'!F33+'1.2'!F41)) -> 4399.9658 | G75: ч.
B78: затраты на возмещение потерь электроэнергии
D80: =('1.5'!I219+'1.5'!I146)*'1.1'!O34*E71 -> 497.70847 | E80: тыс.руб.
C82: цена на электроэнергию
C83: расчетные потери электроэнергии в сети
B86: сумарные издержки
E88: =D61+D53+D80 -> 3878.4253 | F88: тыс.руб.
B91: ДЗ = | C91: =D50+(E88/(1+'1.1'!O32/100)) -> 452294.88 | D91: тыс.руб.
B101: Кольцевая сеть
B103: Кап вложения в ЛЭП
B105: участок | C105: Uном кВ | D105: Район | E105: марка | F105: число | G105: тип | H105: длина | I105: стоимость тыс. руб.
D106: ОЭС | E106: провода | F106: цепей | G106: опор | H106: линии км | I106: 1 км | J106: сумма
B107: 1-3 | C107: 110 | D107: сибирь | E107: АС - 70/11 | F107: 1 | G107: ж/б | H107: ='1.1'!G104 -> 28 | I107: 57 | J107: =I107*H113*H107*H114*F107 -> 76608
B108: 1-4 | C108: 110 | D108: сибирь | E108: АС - 70/11 | F108: 1 | G108: ж/б | H108: ='1.1'!H104 -> 29 | I108: 57 | J108: =I108*H113*H108*H114*F108 -> 79344
B109: 4-3 | C109: 110 | D109: сибирь | E109: АС - 70/11 | F109: 1 | G109: ж/б | H109: ='1.1'!K104 -> 35 | I109: 57 | J109: =I109*H113*H109*H114*F109 -> 95760
I110: Итого | J110: =SUM(J107:J109) -> 251712
B113: Коэффициент удорожания Кдэф. (дефирования) принимаем = | H113: 40
B114: Зональный повышающий коэффициент на стоимость kуд. = | H114: 1.2
B118: Капитальные вложения в ПС
E120: =H128+C124*C122*H113 -> 140480 | F120: тыс.руб.
C122: 430 | D122: тыс.руб.
C124: 2 | D124: - число подстанций
C126: 3 | D126: - число выключателей
H128: =(C124*C132+C124*C126*C130)*H113*H114 -> 106080 | I128: тыс.руб.
C130: 290 | D130: тыс.руб.
C132: 235 | D132: тыс.руб. | E132: по[2 П2.10]
B134: Сумарные вложения
D136: =J110+E120 -> 392192 | E136: тыс.руб.
B140: Ежегодные издержки на амортизацию и обслуживание ПС
D142: =I146*H128*I145/100/100 -> 3317.1216 | E142: тыс.руб.
B145: составляющая стоимости оборудования по ПС | I145: 53 | J145: %
B146: α - нормы отчислений на ремонты и обслуживание для ПС | I146: 5.9 | J146: %
B151: Ежегодные издержки на амортизацию и обслуживание ЛЭП
D153: =I157*I156*J110/100/100 -> 140.95872 | E153: тыс.руб.
B156: составляющая стоимости оборудования по ВЛ | I156: 7 | J156: %
B157: α - нормы отчислений на ремонты и обслуживание для ВЛ | I157: 0.8 | J157: %
B160: определим средневзвешенное время максимальных потерь τ
E163: =(0.124+(F167/10000))^2*8760 -> 2786.4872 | F163: ч.
F167: =(SQRT((('1.2'!F29+'1.2'!F37)*'1.1'!O13)^2+(('1.2'!F31+'1.2'!F39)*'1.1'!O13)^2)/('1.2'!F33+'1.2'!F41)) -> 4399.9658 | G167: ч.
B170: затраты на возмещение потерь электроэнергии
D172: =('1.5'!I146+'1.5'!I219)*'1.1'!O34*E163 -> 497.70847 | E172: тыс.руб.
C174: цена на электроэнергию
C175: расчетные потери электроэнергии в сети
B178: сумарные издержки
E180: =D153+D142+D172 -> 3955.7888 | F180: тыс.руб.
B183: ДЗ = | C183: =D136+(E180/(1+'1.1'!O32/100)) -> 395723.95 | D183: тыс.руб.
B186: Сравнение технико-экономических показателей вариантов сети
D189: схема сети | E189: КЛЭП тыс.руб. | F189: КПС тыс.руб. | G189: И тыс.руб. | H189: ДЗ тыс.руб.
D190: радиальная | E190: =J22 -> 311904 | F190: =E31 -> 136928 | G190: =E88 -> 3878.4253 | H190: =C91 -> 452294.88
D191: кольцевая | E191: =J110 -> 251712 | F191: =E120 -> 140480 | G191: =E180 -> 3955.7888 | H191: =C183 -> 395723.95
C193: разница между вариантами составляет:
F196: =((H190-H191)/H190)*100 -> 12.507532 | G196: %
C199: В дальнейшем проектировании будет рассматриваться | H199: =IF(H190>H191,"кольцевая схема","радиальная схема") -> кольцевая схема

Sheet УР на ПК
J23: ='1.1'!O18 -> 1.06
F24: ='1.1'!O19 -> 1.01
B57: число | D57: мощн.
A58: № ПС | B58: тр-ров | D58: тр-ра
B59: на ПС | D59: МВА | E59: ВН | F59: СН | G59: НН | H59: кВт | I59: кВар | J59: ВН | K59: СН | L59: НН | M59: ВН | N59: СН | O59: НН
A60: 1 | B60: 2 | C60: АТДЦТН-125000/220/110 | D60: 125 | E60: 230 | F60: 121 | G60: 10.5 | H60: 65 | I60: 625 | J60: 0.52 | K60: 0.52 | L60: 3.2 | M60: 49 | N60: 0 | O60: 131
A61: 1 | B61: 2 | C61: ЛТДН - 40000/10 | D61: 40 | E61: =G60 -> 10.5 | G61: 11 | H61: 18.5 | O61: 0.03
A62: 2 | B62: 2 | C62: ТРДН-25000/110/10,5 | D62: 25 | E62: 115 | G62: 10.5 | H62: 27 | I62: 175 | J62: 2.54 | M62: 55.9
A63: 3 | B63: 2 | C63: ТДН-16000/110/11 | D63: 16 | E63: 115 | G63: 11 | H63: 19 | I63: 112 | J63: 4.38 | M63: 86.7
A64: 4 | B64: 2 | C64: ТДН-10000/110/11 | D64: 10 | E64: 115 | G64: 11 | H64: 14 | I64: 70 | J64: 7.95 | M64: 139
C68: таблица регулировочных характеристик выбранных трансформаторов
B71: № ПС | C71: тип тр-ра | D71: предел регулирования | H71: КТ | I71: шаг регулирования | L71: шаг регулирования
I72: по напряжению, кВ | L72: по коэф. трасформации
B73: 1 | C73: =C60 -> АТДЦТН-125000/220/110 | E73: +/- 6х | F73: 2 | G73: % | H73: =F60/E60 -> 0.52608696 | J73: =F60*F73/100 -> 2.42 | M73: =H73*J73/F60 -> 0.010521739
B74: 1 | C74: =C61 -> ЛТДН - 40000/10 | E74: +/- 10х | F74: 1.5 | G74: % | H74: =G61/E61 -> 1.047619 | J74: =G61*F74/100 -> 0.165 | M74: =H74*J74/G61 -> 0.015714286
B75: 2 | C75: =C62 -> ТРДН-25000/110/10,5 | E75: +/- 9х | F75: 1.78 | G75: % | H75: =G62/E62 -> 0.091304348 | J75: =G62*F75/100 -> 0.1869 | M75: =H75*J75/G62 -> 0.0016252174
B76: 3 | C76: =C63 -> ТДН-16000/110/11 | E76: +/- 9х | F76: 1.78 | G76: % | H76: =G63/E63 -> 0.095652174 | J76: =G63*F76/100 -> 0.1958 | M76: =H76*J76/G63 -> 0.0017026087
B77: 4 | C77: =C64 -> ТДН-10000/110/11 | E77: +/- 9х | F77: 1.78 | G77: % | H77: =G64/E64 -> 0.095652174 | J77: =G64*F77/100 -> 0.1958 | M77: =H77*J77/G64 -> 0.0017026087
C81: таблица выбранного предела регулирования трансформаторов
B84: № ПС | C84: тип тр-ра | D84: выбраная отпайка, предел регулирования, в режиме нагрузок:
D85: max | E85: КТ | F85: min | G85: КТ | H85: ПА1 | I85: КТ | J85: ПА2 | K85: КТ | L85: ПА3 | M85: КТ | N85: ПА4 | O85: КТ
B86: 1 | C86: =C60 -> АТДЦТН-125000/220/110 | D86: =(E86-H73)/M73 -> 6 | E86: =H73+M73+M73+M73+M73+M73+M73 -> 0.58921739 | F86: =(G86-H73)/M73 -> 6 | G86: =H73+M73++M73+M73+M73+M73+M73 -> 0.58921739 | H86: =(I86-H73)/M73 -> 6 | I86: =H73+M73+M73+M73+M73+M73+M73 -> 0.58921739 | J86: =(K86-H73)/M73 -> 6 | K86: =H73+M73+M73+M73+M73+M73+M73 -> 0.58921739 | L86: =(M86-H73)/M73 -> 6 | M86: =H73+M73+M73+M73+M73+M73+M73 -> 0.58921739 | N86: =(O86-H73)/M73 -> 6 | O86: =H73+M73+M73+M73+M73+M73+M73 -> 0.58921739
B87: 1 | C87: =C61 -> ЛТДН - 40000/10 | D87: =(E87-H74)/M74 -> 10 | E87: =H74+M74+M74+M74+M74+M74+M74+M74+M74+M74+M74 -> 1.2047619 | F87: =(G87-H74)/M74 -> 10 | G87: =H74+M74+M74+M74+M74+M74+M74+M74+M74+M74+M74 -> 1.2047619 | H87: =(I87-H74)/M74 -> 1 | I87: =H74+M74 -> 1.0633333 | J87: =(K87-H74)/M74 -> -1 | K87: =H74-M74 -> 1.0319048 | L87: =(M87-H74)/M74 -> 10 | M87: =H74+M74+M74+M74+M74+M74+M74+M74+M74+M74+M74 -> 1.2047619 | N87: =(O87-H74)/M74 -> 10 | O87: =H74+M74+M74+M74+M74+M74+M74+M74+M74+M74+M74 -> 1.2047619
B88: 2 | C88: =C62 -> ТРДН-25000/110/10,5 | D88: =(E88-H75)/M75 -> 1 | E88: =H75+M75 -> 0.092929565 | F88: =(G88-H75)/M75 -> -2 | G88: =H75-M75-M75 -> 0.088053913 | H88: =(I88-H75)/M75 -> 0 | I88: =H75 -> 0.091304348 | J88: =(K88-H75)/M75 -> 1 | K88: =H75+M75 -> 0.092929565 | L88: =(M88-H75)/M75 -> 1 | M88: =H75+M75 -> 0.092929565 | N88: =(O88-H75)/M75 -> 4 | O88: =H75+M75+M75+M75+M75 -> 0.097805217
B89: 3 | C89: =C63 -> ТДН-16000/110/11 | D89: =(E89-H76)/M76 -> 1 | E89: =H76+M76 -> 0.097354783 | F89: =(G89-H76)/M76 -> -3 | G89: =H76-M76-M76-M76 -> 0.090544348 | H89: =(I89-H76)/M76 -> -1 | I89: =H76-M76 -> 0.093949565 | J89: =(K89-H76)/M76 -> 0 | K89: =H76 -> 0.095652174 | L89: =(M89-H76)/M76 -> 1 | M89: =H76+M76 -> 0.097354783 | N89: =(O89-H76)/M76 -> 1 | O89: =H76+M76 -> 0.097354783
B90: 4 | C90: =C64 -> ТДН-10000/110/11 | D90: =(E90-H77)/M77 -> 0 | E90: =H77 -> 0.095652174 | F90: =(G90-H77)/M77 -> -3 | G90: =H77-M77-M77-M77 -> 0.090544348 | H90: =(I90-H77)/M77 -> -1 | I90: =H77-M77 -> 0.093949565 | J90: =(K90-H77)/M77 -> 0 | K90: =H77 -> 0.095652174 | L90: =(M90-H77)/M77 -> 2 | M90: =H77+M77+M77 -> 0.099057391 | N90: =(O90-H77)/M77 -> 0 | O90: =H77 -> 0.095652174

Sheet ТЭП
E2: Определение технико-экономических показателей электрической сети
B4: Капитальные вложения в воздушные линии сведены в таблицу
E7: Марка | F7: кол-во | G7: тип | H7: длинна | I7: стоимость тыс. руб.
B8: участок | C8: Uном; кВ | D8: Район ОЭС | E8: провода | F8: цепей | G8: опор | H8: линии | I8: 1 км. | J8: сумма
B9: А-1 | C9: 220 | D9: Сибирь | E9: АС-240/32 | F9: 2 | G9: ст. | H9: ='1.1'!E104 -> 57 | I9: 88 | J9: =H16*F9*H9*I9*H17 -> 481536
B10: 1-2 | C10: 110 | D10: Сибирь | E10: АС - 95/16 | F10: 2 | G10: ж/б | H10: ='1.1'!F104 -> 28 | I10: 38 | J10: =H16*F10*H10*I10*H17 -> 102144
B11: 1-3 | C11: 110 | D11: Сибирь | E11: АС - 70/11 | F11: 1 | G11: ж/б | H11: ='1.1'!G104 -> 28 | I11: 34 | J11: =H16*F11*H11*I11*H17 -> 45696
B12: 1-4 | C12: 110 | D12: Сибирь | E12: АС - 70/11 | F12: 1 | G12: ж/б | H12: ='1.1'!H104 -> 29 | I12: 34 | J12: =H16*F12*H12*I12*H17 -> 47328
B13: 3-4 | C13: 110 | D13: Сибирь | E13: АС - 70/11 | F13: 1 | G13: ж/б | H13: ='1.1'!K104 -> 35 | I13: 34 | J13: =H16*F13*H13*I13*H17 -> 57120
I14: Итого | J14: =SUM(J9:J13) -> 733824
B16: Коэффициент удорожания Кдэф. (дефирования) принимаем = | H16: =ТЭС!H113 -> 40
B17: Зональный повышающий коэффициент на стоимость kуд. = | H17: =ТЭС!H114 -> 1.2
B19: Капитальные вложения в ПС сведены в таблицу
B21: Наименование и тип элементов ПС | G21: кол-во | H21: стоимость тыс.руб.
H22: единици | I22: всего
B23: ПС А
B24: 1. выключатели РУВН | G24: 2 | H24: 600 | I24: =H16*G24*H24*H17 -> 57600
B25: ПС 1
B26: 1. выключатели РУВН | G26: 4 | H26: 210 | I26: =H26*G26*H16*H17 -> 40320
B27: 2. выключатели РУСН | G27: 10 | H27: 290 | I27: =H27*G27*H16*H17 -> 139200
B28: 3. выключатели РУНН | G28: 3 | H28: 4.6 | I28: =H28*G28*H16*H17 -> 662.4
B29: 4. трансформатор АТДЦТН - 125000/220/110 | G29: 2 | H29: 621 | I29: =H29*G29*H16*H17 -> 59616
B30: 5. трансформатор ЛТДН - 40000/10 | G30: 2 | H30: 150 | I30: =H30*G30*H16*H17 -> 14400
B31: 6. постоянная часть затрат:
C32: сборные шины | G32: 1 | H32: 490 | I32: =H32*G32*H16*H17 -> 23520
C33: мостик | G33: 1 | H33: 430 | I33: =H33*G33*H16*H17 -> 20640
B34: 7, СТК
B35: ПС 2
B36: 1. выключатели РУВН | G36: 2 | H36: 290 | I36: =H36*G36*H16*H17 -> 27840
B37: 2. выключатели РУНН | G37: 2 | H37: 4.6 | I37: =H37*G37*H16*H17 -> 441.6
B38: 3. трансформатор ТРДН-25000/110/10,5 | G38: 2 | H38: 222 | I38: =H38*G38*H16*H17 -> 21312
B39: 4. постоянная часть затрат:
B40: два блока с выключателем и неавтоматической | G40: 1 | H40: 198 | I40: =H40*G40*H16*H17 -> 9504
B41: перемычкой со стороны линий
B42: ПС 3
B43: 1. выключатели РУВН | G43: 2 | H43: 290 | I43: =H43*G43*H16*H17 -> 27840
B44: 2. выключатели РУНН | G44: 3 | H44: 4.6 | I44: =H44*G44*H16*H17 -> 662.4
B45: 3. трансформатор ТРДН-16000/110/11 | G45: 2 | H45: 172 | I45: =H45*G45*H16*H17 -> 16512
B46: 4. постоянная часть затрат:
B47: мостик с выключателями в цепях линий | G47: 1 | H47: 235 | I47: =H47*G47*H16*H17 -> 11280
B48: и ремонтной перемычкой со стороны линий
B52: ПС 4
B53: 1. выключатели РУВН | G53: 2 | H53: 290 | I53: =H53*G53*H16*H17 -> 27840
B54: 2. выключатели РУНН | G54: 3 | H54: 4.6 | I54: =H54*G54*H16*H17 -> 662.4
B55: 3. трансформатор ТРДН-16000/110/11 | G55: 2 | H55: 172 | I55: =H55*G55*H16*H17 -> 16512
B56: 4. постоянная часть затрат:
B57: мостик с выключателями в цепях линий | G57: 1 | H57: 235 | I57: =H57*G57*H16*H17 -> 11280
B58: и ремонтной перемычкой со стороны линий
H59: Итого | I59: =SUM(I24:I58) -> 527644.8
B63: Капитальные вложения в ПС безучета постоянной части затрат
D65: =I59-I57-I47-I40-I33-I32 -> 451420.8 | E65: тыс.руб.
B68: Сумарные вложения в сеть
D70: =J14+I59 -> 1261468.8 | E70: тыс.руб.
B73: Ежегодные издержки на амортизацию и обслуживание ПС
D75: =H79*D65*H78/100/100 -> 14115.928 | E75: тыс.руб.
B78: составляющая стоимости оборудования по ПС | H78: 53 | I78: %
B79: α - нормы отчислений на ремонты и обслуживание для ПС | H79: 5.9 | I79: %
B82: Ежегодные издержки на амортизацию и обслуживание ЛЭП
D84: =H88*H87*J14/100/100 -> 410.94144 | E84: тыс.руб.
B87: составляющая стоимости оборудования по ВЛ | H87: 7 | I87: %
B88: α - нормы отчислений на ремонты и обслуживание для ВЛ | H88: 0.8 | I88: %
B91: определим средневзвешенное время максимальных потерь τ
E94: =(0.124+(F98/10000))^2*8760 -> 2592.0995 | F94: ч.
F98: =(SQRT(('1.2'!F45*'1.1'!O12)^2+('1.2'!F49*'1.1'!O12)^2)/'1.2'!F53) -> 4199.6854 | G98: ч.
B102: затраты на возмещение потерь электроэнергии
D104: =('1.5'!E25+'1.5'!E76+'1.5'!E96+'1.5'!E169+'1.5'!E248+'1.5'!E264+'1.5'!E280+'1.5'!E332+'1.6'!E62+'1.6'!E114)*'1.1'!O34*E94 -> 33346.729 | E104: тыс.руб.
C106: цена на электроэнергию
C107: полные расчетные потери электроэнергии в сети
E109: =('1.5'!E25+'1.5'!E76+'1.5'!E96+'1.5'!E169+'1.5'!E248+'1.5'!E264+'1.5'!E280+'1.5'!E332+'1.6'!E62+'1.6'!E114)*F98 -> 54027.93 | F109: Вт
B111: сумарные издержки
E113: =D84+D75+D104 -> 47873.599 | F113: тыс.руб.
B116: ДЗ = | C116: =D70+(E113/(1+'1.1'!O32/100)) -> 1304213.1 | D116: тыс.руб. | E116: на первый год строительства
A119: Расчет себестоимости передачи электроэнергии. Определение КПД сети
D122: =E113/('1.2'!F45*8000)*10^2 -> 4.7873599 | E122: коп./кВт.ч.
B125: суммарная энергия, потребляемая потребителем за год
E128: ='1.2'!F45*8000 -> 1000000 | F128: МВт
B131: потери энергии в сети за год составляют
F134: =E109*100/(E128*10^6) -> 5.402793e-06 | G134: %
B138: средневзвешенный КПД сети
F141: =E128*10^6/(E128*10^6+E109)*100 -> 99.999995 | G141: %
B145: максимальный КПД сети
F148: ='1.2'!F45*10^6/('1.2'!F45*10^6+'1.5'!E25+'1.5'!E76+'1.5'!E96+'1.5'!E169+'1.5'!E248+'1.5'!E264+'1.5'!E280+'1.5'!E332+'1.6'!E62+'1.6'!E114)*100 -> 99.99999 | G148: %

Sheet Список литературы
C2: Список используемой литературы:
A5: 1 | B5: Справочник по проектированию электрических сетей
B6: /Д.Л. Фабисович – М.:Изд-во НЦ ЭНАС, 2005/
A8: 2 | B8: Электрическая сеть района нагрузок: Учедное пособие к курсовому проекту
B9: /О.А. Бушуева, А.И. Кулешов - Изд. ГОУВПО ИГЭУ им. В.И. Ленина. - Иваново 2006/
A11: 3 | B11: Выбор силовых трансформаторов подстанций энергосистем и промышленных
B12: предприятий с учётом допустимых нагрузок
B13: /М.И. Соколов - Изд. ГОУВПО ИГЭУ им. В.И. Ленина. - Иваново 1999/
A15: 4 | B15: Расчёт установившихся режимов электрических сетей. Методические указания
B16: /О.А. Бушуева,Н.Н. Парфёнычева А.И. Кулешов - Изд. ГОУВПО ИГЭУ им.
B17: В.И. Ленина. - Иваново 2006/
A19: 5 | B19: Применение типовых схем распределительных устройств понижающих подстанций
B20: /О.А. Бушуева, А.А. Мартиросян - Изд. ГОУВПО ИГЭУ им. В.И. Ленина. - Иваново 2006/
A22: 6 | B22: Определение потерь мощности и энергии в электрических сетях.
B23: Методические указания /Бушуева О.А. Иван. гос. ин-т - Иваново 1990/
